Metadata-Version: 2.1
Name: odoo13-addon-shopinvader-product-stock-state
Version: 13.0.1.0.1
Summary: This module is used to choose a stock state during theexport (by backend)
Home-page: https://akretion.com
Author: Akretion
License: AGPL-3
Platform: UNKNOWN
Classifier: Programming Language :: Python
Classifier: Framework :: Odoo
Classifier: License :: OSI Approved :: GNU Affero General Public License v3
Requires-Python: >=3.5
Requires-Dist: odoo13-addon-product-stock-state
Requires-Dist: odoo13-addon-shopinvader-product-stock
Requires-Dist: odoo (<13.1dev,>=13.0a)
